basecampapi/__init__.py
basecampapi/basecamp.py
basecampapi/endpoints/__init__.py
basecampapi/endpoints/attachments.py
basecampapi/endpoints/campfire.py
basecampapi/endpoints/chatbot.py
basecampapi/endpoints/comments.py
basecampapi/endpoints/messageboard.py
basecampapi/endpoints/todolist.py
basecampapi/endpoints/todoset.py
basecampapi-2.0.0.dist-info/LICENSE
basecampapi-2.0.0.dist-info/METADATA
basecampapi-2.0.0.dist-info/WHEEL
basecampapi-2.0.0.dist-info/RECORD
