Metadata-Version: 2.1
Name: basecampapi
Version: 2.0.0
Summary: A Python wrapper for the Basecamp 3 API that provides a simple and intuitive interface for interacting with Basecamp resources.
Home-page: https://github.com/mare011rs/basecampapi
License: MIT
Keywords: basecamp,api,wrapper,basecamp3,client
Author: mare011rs
Author-email: mare011rs@gmail.com
Requires-Python: >=3.7,<4.0
Classifier: Development Status :: 5 - Production/Stable
Classifier: Intended Audience :: Developers
Classifier: License :: OSI Approved :: MIT License
Classifier: Programming Language :: Python :: 3
Classifier: Programming Language :: Python :: 3.7
Classifier: Programming Language :: Python :: 3.8
Classifier: Programming Language :: Python :: 3.9
Classifier: Programming Language :: Python :: 3.10
Classifier: Programming Language :: Python :: 3.11
Classifier: Programming Language :: Python :: 3.12
Classifier: Programming Language :: Python :: 3.13
Classifier: Topic :: Software Development :: Libraries :: Python Modules
Requires-Dist: filetype (>=1.2.0,<2.0.0)
Requires-Dist: requests (>=2.25.0,<3.0.0)
Project-URL: Repository, https://github.com/mare011rs/basecampapi
